{"children":[{"name":"Line 117","style":{"@mini":{"display":"none"},"@mobile":{"display":"none"},"@small":{"display":"flex"},"@tablet":{"display":"none"},"alignItems":"center","background":"linear-gradient(291.18deg, rgb(29, 69, 36) 0%, rgb(254, 254, 190) 100%)","display":"flex","flexDirection":"column","height":"1px","justifyContent":"center","width":"100%"},"uuid":"dace76ac-ba79-4310-8e57-b278928d3980","children":[]},{"children":[{"children":[{"children":[{"children":[{"content":{"data":"{{text1.value}}","type":"richText"},"name":"國本 知里","style":{"@mobile":{"fontSize":"22px","lineHeight":"1.40"},"@tablet":{"fontSize":"24px"},"color":"#1D4524","flex":"none","fontFamily":"var(--s-font-3e96c90c)","fontSize":"30px","fontStyle":"normal","height":"auto","letterSpacing":"0.1em","lineHeight":"1.2","p":{"margin":"0px 0px 0px 0px"},"strong":{"@mobile":{"fontSize":"18px"},"@tablet":{"fontSize":"24px"},"color":"#4D5755","fontWeight":"600"},"textAlign":"left","width":"auto"},"uuid":"9d86b236-e5f1-4943-98c0-f8cfec4999c9","children":[]},{"content":{"data":"{{text9.value}}","type":"text"},"name":"Cynthialy株式会社 代表取締役","style":{"@mobile":{"fontSize":"13px"},"@tablet":{"fontSize":"14px"},"color":"#4D5755","flex":"none","fontFamily":"var(--s-font-f69ce839)","fontSize":"16px","fontStyle":"normal","height":"auto","letterSpacing":"0.1em","lineHeight":"1.2","textAlign":"left","width":"auto"},"uuid":"2fa1fc5e-7a5c-4dea-afb1-408da038c3f7","children":[]}],"name":"Container","style":{"@mobile":{"gap":"4px","padding":"0px"},"alignContent":"flex-start","alignItems":"flex-start","flex":"1","flexDirection":"column","flexWrap":"nowrap","gap":"12px","height":"auto","justifyContent":"flex-start","padding":"0px","width":"auto"},"uuid":"f578e5b0-095a-4998-9e3a-4544cb0e1ee0"},{"children":[{"children":[{"content":{"src":"{{image10.value}}","type":"img"},"link":{"newTab":false,"path":"{{url1.value}}"},"name":"icon","style":{"alignItems":"center","flex":"none","flexDirection":"column","height":"auto","justifyContent":"center","overflowX":"hidden","overflowY":"hidden","width":"auto"},"uuid":"f9123e33-663a-4a96-9ce7-f4e7c31a1d21","children":[]}],"link":{"newTab":false,"path":"{{url1.value}}"},"name":"Group","style":{"@mobile":{"gap":"16px"},"alignContent":"center","alignItems":"center","flexDirection":"row","flexWrap":"nowrap","gap":"40px","height":"auto","justifyContent":"space-between","padding":"0px"},"tagName":"div","uuid":"63929a2f-20b6-450c-998b-626edb91dc52"}],"name":"Group","style":{"@mobile":{"gap":"16px"},"alignContent":"center","alignItems":"center","flexDirection":"row","flexWrap":"nowrap","gap":"40px","justifyContent":"space-between","padding":"0px","width":"auto"},"tagName":"div","uuid":"0b530fb8-6fc3-4023-9b02-8f8792121e7a"}],"name":"Frame 627811","style":{"@mobile":{"gap":"16px","padding":"0px"},"alignContent":"center","alignItems":"center","flex":"none","flexDirection":"row","flexWrap":"nowrap","gap":"40px","height":"auto","justifyContent":"space-between","padding":"0px 0px 0px 0px","width":"100%"},"uuid":"ae433949-391f-46de-b1cd-3300a8455bd3"},{"children":[{"children":[{"name":"Ellipse 95","style":{"alignItems":"center","background":"linear-gradient(270deg, rgb(29, 69, 36) 0%, rgb(123, 146, 101) 100%)","borderRadius":"50%","flex":"none","flexDirection":"column","height":"10px","justifyContent":"center","width":"10px"},"uuid":"58b2dcc2-4150-4cf3-8fbf-31f3b5270e06","children":[]},{"content":{"data":"{{text14.value}}","type":"text"},"name":"生成AI基礎・リテラシー","style":{"@mobile":{"fontSize":"13px"},"@tablet":{"fontSize":"15px"},"color":"#0E2623","flex":"none","fontFamily":"'秀英角ゴシック銀 M JIS2004'","fontSize":"18px","fontStyle":"normal","fontWeight":"400","height":"auto","letterSpacing":"0.1em","lineHeight":"1.2","textAlign":"center","width":"auto"},"uuid":"b0d4e8c7-380a-47e8-8c56-598987eff9bb","children":[]}],"name":"Item","style":{"@mobile":{"gap":"4px","padding":"4px 0px 4px 0px"},"alignContent":"center","alignItems":"center","flex":"none","flexDirection":"row","flexWrap":"nowrap","gap":"12px","height":"auto","justifyContent":"center","padding":"12px 0px 12px 0px","width":"auto"},"tagName":"li","uuid":"b2f1b9a3-a0df-4378-be45-970a2f0c78e0"},{"children":[{"name":"Ellipse 95","style":{"alignItems":"center","background":"linear-gradient(270deg, rgb(29, 69, 36) 0%, rgb(123, 146, 101) 100%)","borderRadius":"50%","flex":"none","flexDirection":"column","height":"10px","justifyContent":"center","width":"10px"},"uuid":"6bc363b0-c200-424d-b4d2-74a9a48d7142","children":[]},{"content":{"data":"{{text17.value}}","type":"text"},"name":"生成AI×新規事業","style":{"@mobile":{"fontSize":"13px"},"@tablet":{"fontSize":"15px"},"color":"#0E2623","flex":"none","fontFamily":"'秀英角ゴシック銀 M JIS2004'","fontSize":"18px","fontStyle":"normal","fontWeight":"400","height":"auto","letterSpacing":"0.1em","lineHeight":"1.2","textAlign":"center","width":"auto"},"uuid":"810312e5-23af-4a66-9a98-66b972df6e49","children":[]}],"name":"Item","style":{"@mobile":{"gap":"4px","padding":"4px 0px 4px 0px"},"alignContent":"center","alignItems":"center","flex":"none","flexDirection":"row","flexWrap":"nowrap","gap":"12px","height":"auto","justifyContent":"center","padding":"12px 0px 12px 0px","width":"auto"},"tagName":"li","uuid":"2ec420cb-355b-4d37-9742-b2f6a30c399a"}],"name":"Container","style":{"@mobile":{"alignContent":"flex-start","alignItems":"flex-start","flexDirection":"column","flexWrap":"nowrap","gap":"16px","justifyContent":"flex-start","padding":"25px 16px 25px 26px"},"@small":{"gap":"0px 34px"},"alignContent":"center","alignItems":"center","background":"#F1F1F1","borderRadius":"4px","flexDirection":"row","flexWrap":"wrap","gap":"34px","height":"auto","justifyContent":"flex-start","padding":"4px 25px 4px 25px","width":"100%"},"tagName":"ul","uuid":"72e186b4-4789-4362-926a-ac4be1a4dbb1"}],"name":"Frame 627809","style":{"@mobile":{"gap":"12px","padding":"0px"},"alignContent":"flex-start","alignItems":"flex-start","flexDirection":"column","flexWrap":"nowrap","gap":"27px","height":"auto","justifyContent":"flex-start","padding":"0px","width":"100%"},"uuid":"b6fc3a8c-b814-45b2-99b9-31223e261112"},{"children":[{"content":{"data":"{{text19.value}}","type":"text"},"name":"早稲田大学大学院卒業後、外資ITのSAPにてHR SaaSエンタープライズ営業、北欧マーケティングリサーチプラットフォームベンチャーにてアジア領域の事業開発等を経験。その後、AIスタートアップ・Cinnamon AIの事業開発マネージャーを経て、1社創業しAIスタートアップ複数社のマーケティング・広報立ち上げ支援、DXスタートアップ向けのハイクラスエージェントを立ち上げ等。2022年10月にシンシアリー創業。","style":{"@mini":{"fontSize":"16px"},"@mobile":{"fontSize":"14px","lineHeight":"1.80"},"@tablet":{"fontSize":"14px"},"color":"#030807","flex":"1","fontFamily":"var(--s-font-f69ce839)","fontSize":"16px","fontStyle":"normal","height":"auto","letterSpacing":"0.1em","lineHeight":"1.6","overflowX":"hidden","overflowY":"hidden","textAlign":"left"},"uuid":"3de94ec2-2bb6-4367-b140-972a50ab75ca","children":[]}],"name":"Paragraph","style":{"@mobile":{"gap":"4px"},"alignContent":"center","alignItems":"center","flexDirection":"row","flexWrap":"nowrap","gap":"10px","height":"auto","justifyContent":"center","padding":"0px","width":"100%"},"uuid":"89063104-8719-4132-b9c6-2e13cdf77c39"}],"name":"Frame 627810","style":{"@mobile":{"gap":"16px","padding":"0px"},"alignContent":"flex-start","alignItems":"flex-start","flexDirection":"column","flexWrap":"nowrap","gap":"35px","height":"auto","justifyContent":"flex-start","padding":"0px","width":"680px"},"uuid":"72a8ce14-1626-4e7c-8b1a-c2e5cd4c0afc"}],"defs":[{"key":"text9","type":"string","uid":"YPJgeCAQ"},{"key":"image10","type":"image","uid":"eD6sr3H_"},{"key":"text14","type":"string","uid":"fowdKqfK"},{"key":"text17","type":"string","uid":"TpyLTjTq"},{"key":"text19","type":"string","uid":"p6OfNiXF"},{"key":"text1","type":"string","uid":"090mTyXT"},{"key":"url1","type":"url","uid":"KstRH8sN"},{"key":"url2","type":"url","uid":"NdIocjjN"}],"name":"Container","state":{"image10":"https://storage.googleapis.com/studio-design-asset-files/projects/XKOk2PZ6W4/s-24x24_7687e94c-a4ff-467b-9f39-903c4f6039ff.svg","text1":"Hello World.","text14":"生成AI基礎・リテラシー","text17":"生成AI×新規事業","text19":"早稲田大学大学院卒業後、外資ITのSAPにてHR SaaSエンタープライズ営業、北欧マーケティングリサーチプラットフォームベンチャーにてアジア領域の事業開発等を経験。その後、AIスタートアップ・Cinnamon AIの事業開発マネージャーを経て、1社創業しAIスタートアップ複数社のマーケティング・広報立ち上げ支援、DXスタートアップ向けのハイクラスエージェントを立ち上げ等。2022年10月にシンシアリー創業。","text9":"Cynthialy株式会社 代表取締役","url1":"","url2":""},"style":{"@mobile":{"gap":"16px","padding":"0px"},"@tablet":{"alignContent":"center","alignItems":"center","flex":"none","justifyContent":"flex-start","width":"100%"},"alignContent":"flex-start","alignItems":"flex-start","flex":"1","flexDirection":"column","flexWrap":"nowrap","gap":"35px","height":"auto","justifyContent":"flex-start","overflowX":"hidden","overflowY":"hidden","padding":"0px","width":"auto"},"type":"component","uuid":"64a623b4-779f-4d99-8e0c-f9244a7106fe"}